{
  "sections": {
    "main": {
      "type": "main-product",
      "blocks": {
        "vendor": {
          "type": "text",
          "settings": {
            "text": "{{ product.vendor }}",
            "text_style": "uppercase"
          }
        },
        "title": {
          "type": "title",
          "settings": {
          }
        },
        "price": {
          "type": "price",
          "settings": {
          }
        },
        "variant_picker": {
          "type": "variant_picker",
          "settings": {
            "picker_type": "button"
          }
        },
        "quantity_selector": {
          "type": "quantity_selector",
          "settings": {
          }
        },
        "buy_buttons": {
          "type": "buy_buttons",
          "settings": {
            "show_dynamic_checkout": false,
            "show_gift_card_recipient": true
          }
        },
        "description": {
          "type": "description",
          "settings": {
          }
        },
        "share": {
          "type": "share",
          "settings": {
            "share_label": "Share"
          }
        }
      },
      "block_order": [
        "vendor",
        "title",
        "price",
        "variant_picker",
        "quantity_selector",
        "buy_buttons",
        "description",
        "share"
      ],
      "settings": {
        "enable_sticky_info": true,
        "color_scheme": "",
        "media_size": "large",
        "constrain_to_viewport": true,
        "media_fit": "contain",
        "gallery_layout": "thumbnail",
        "media_position": "left",
        "image_zoom": "hover",
        "mobile_thumbnails": "show",
        "hide_variants": true,
        "enable_video_looping": false,
        "padding_top": 36,
        "padding_bottom": 12
      }
    },
    "related-products": {
      "type": "related-products",
      "disabled": true,
      "settings": {
        "heading": "También podría interesarte",
        "heading_size": "h2",
        "products_to_show": 4,
        "columns_desktop": 4,
        "color_scheme": "background-1",
        "image_ratio": "square",
        "image_shape": "default",
        "show_secondary_image": true,
        "show_vendor": false,
        "show_rating": false,
        "columns_mobile": "2",
        "padding_top": 36,
        "padding_bottom": 28
      }
    },
    "6faa177a-291e-4eac-a327-cec0acd70713": {
      "type": "image-banner",
      "settings": {
        "image": "shopify:\/\/shop_images\/racing-through-city.jpg",
        "image_2": "shopify:\/\/shop_images\/fast-bike-racing.jpg",
        "image_overlay_opacity": 0,
        "image_height": "small",
        "desktop_content_position": "middle-center",
        "show_text_box": true,
        "desktop_content_alignment": "center",
        "color_scheme": "",
        "image_behavior": "none",
        "mobile_content_alignment": "center",
        "stack_images_on_mobile": true,
        "show_text_below": true
      }
    },
    "2a759980-49c2-4f5d-b400-194fe2a83f75": {
      "type": "collapsible-content",
      "blocks": {
        "template--21615255552307__2a759980-49c2-4f5d-b400-194fe2a83f75-collapsible_row-1": {
          "type": "collapsible_row",
          "settings": {
            "heading": "Collapsible row",
            "icon": "check_mark",
            "row_content": "",
            "page": ""
          }
        },
        "template--21615255552307__2a759980-49c2-4f5d-b400-194fe2a83f75-collapsible_row-2": {
          "type": "collapsible_row",
          "settings": {
            "heading": "Collapsible row",
            "icon": "check_mark",
            "row_content": "",
            "page": ""
          }
        },
        "template--21615255552307__2a759980-49c2-4f5d-b400-194fe2a83f75-collapsible_row-3": {
          "type": "collapsible_row",
          "settings": {
            "heading": "Collapsible row",
            "icon": "check_mark",
            "row_content": "",
            "page": ""
          }
        },
        "template--21615255552307__2a759980-49c2-4f5d-b400-194fe2a83f75-collapsible_row-4": {
          "type": "collapsible_row",
          "settings": {
            "heading": "Collapsible row",
            "icon": "check_mark",
            "row_content": "",
            "page": ""
          }
        }
      },
      "block_order": [
        "template--21615255552307__2a759980-49c2-4f5d-b400-194fe2a83f75-collapsible_row-1",
        "template--21615255552307__2a759980-49c2-4f5d-b400-194fe2a83f75-collapsible_row-2",
        "template--21615255552307__2a759980-49c2-4f5d-b400-194fe2a83f75-collapsible_row-3",
        "template--21615255552307__2a759980-49c2-4f5d-b400-194fe2a83f75-collapsible_row-4"
      ],
      "settings": {
        "caption": "",
        "heading": "Collapsible content",
        "heading_size": "h1",
        "heading_alignment": "center",
        "layout": "none",
        "color_scheme": "",
        "container_color_scheme": "",
        "open_first_collapsible_row": false,
        "image_ratio": "adapt",
        "desktop_layout": "image_second",
        "padding_top": 36,
        "padding_bottom": 36
      }
    },
    "704f418e-3583-4e12-805d-dcc479f79226": {
      "type": "featured-collection",
      "settings": {
        "title": "Featured collection",
        "heading_size": "h2",
        "description": "",
        "show_description": false,
        "description_style": "body",
        "collection": "frontpage",
        "products_to_show": 4,
        "columns_desktop": 4,
        "full_width": false,
        "show_view_all": true,
        "view_all_style": "solid",
        "enable_desktop_slider": false,
        "color_scheme": "",
        "image_ratio": "adapt",
        "image_shape": "default",
        "show_secondary_image": false,
        "show_vendor": false,
        "show_rating": false,
        "enable_quick_add": false,
        "columns_mobile": "2",
        "swipe_on_mobile": false,
        "padding_top": 36,
        "padding_bottom": 36
      }
    }
  },
  "order": [
    "main",
    "related-products",
    "6faa177a-291e-4eac-a327-cec0acd70713",
    "2a759980-49c2-4f5d-b400-194fe2a83f75",
    "704f418e-3583-4e12-805d-dcc479f79226"
  ]
}
